nasdaqFetcher/__init__.py
nasdaqFetcher/asset_fetcher.py
nasdaqFetcher/data_fetcher.py
nasdaqFetcher/options_fetcher.py
nasdaqFetcher/utils.py
nasdaqfetcher-1.0.0.dist-info/licenses/LICENSE
nasdaqfetcher-1.0.0.dist-info/METADATA
nasdaqfetcher-1.0.0.dist-info/WHEEL
nasdaqfetcher-1.0.0.dist-info/top_level.txt
nasdaqfetcher-1.0.0.dist-info/RECORD
