Metadata-Version: 2.4
Name: nasdaqFetcher
Version: 1.0.0
Summary: Client utilities for fetching market data from Nasdaq
Author: nndjoli
License: MIT
Project-URL: Homepage, https://github.com/nndjoli/nasdaq-data-fetcher
Classifier: Programming Language :: Python :: 3
Classifier: License :: OSI Approved :: MIT License
Classifier: Operating System :: OS Independent
Requires-Python: >=3.10
License-File: LICENSE
Requires-Dist: pandas
Requires-Dist: requests
Requires-Dist: numpy
Requires-Dist: scipy
Requires-Dist: matplotlib
Requires-Dist: seaborn
Dynamic: license-file
